LICENSE
MANIFEST.in
README.rst
VERSION
pyproject.toml
setup.cfg
setup.py
Starlette_OpenTracing.egg-info/PKG-INFO
Starlette_OpenTracing.egg-info/SOURCES.txt
Starlette_OpenTracing.egg-info/dependency_links.txt
Starlette_OpenTracing.egg-info/not-zip-safe
Starlette_OpenTracing.egg-info/requires.txt
Starlette_OpenTracing.egg-info/top_level.txt
starlette_opentracing/__init__.py
starlette_opentracing/middleware.py
tests/__init__.py
tests/conftest.py
tests/test_starlette_tracing.py
tests/test_tracer.py