Metadata-Version: 2.1
Name: Starlette-OpenTracing
Version: 0.0.9
Summary: OpenTracing support for Starlette and FastApi applications
Home-page: http://github.com/acidjunk/starlette-opentracing
Author: René Dohmen
Author-email: acidjunk@gmail.com
License: Apache 2.0
Download-URL: https://github.com/acidjunk/starlette-opentracing/tarball/0.0.9
Platform: any
Classifier: Development Status :: 4 - Beta
Classifier: Environment :: Web Environment
Classifier: Intended Audience :: Developers
Classifier: License :: OSI Approved :: Apache Software License
Classifier: Operating System :: OS Independent
Classifier: Programming Language :: Python
Classifier: Programming Language :: Python :: 3.6
Classifier: Programming Language :: Python :: 3.7
Classifier: Programming Language :: Python :: 3.8
Classifier: Programming Language :: Python :: Implementation :: CPython
Classifier: Programming Language :: Python :: Implementation :: PyPy
Classifier: Topic :: Internet :: WWW/HTTP :: Dynamic Content
Classifier: Topic :: Software Development :: Libraries :: Python Modules
Provides-Extra: tests
